LICENSE
MANIFEST.in
README.rst
setup.py
beegarden/__init__.py
beegarden/core.py
beegarden/honey_holder.py
beegarden/my_bee.py
beegarden/simple_game.py
beegarden.egg-info/PKG-INFO
beegarden.egg-info/SOURCES.txt
beegarden.egg-info/dependency_links.txt
beegarden.egg-info/requires.txt
beegarden.egg-info/top_level.txt
beegarden/themes/__init__.py
beegarden/themes/dark/__init__.py
beegarden/themes/dark/bee-1.png
beegarden/themes/dark/bee-2.png
beegarden/themes/dark/bee-3.png
beegarden/themes/dark/bee-4.png
beegarden/themes/dark/beehive.png
beegarden/themes/dark/flower.png
beegarden/themes/default/__init__.py
beegarden/themes/default/bee-1.png
beegarden/themes/default/bee-2.png
beegarden/themes/default/bee-3.png
beegarden/themes/default/bee-4.png
beegarden/themes/default/bee.png
beegarden/themes/default/beehive.png
beegarden/themes/default/flower.png
beegarden/themes/default/romashka.png