Metadata-Version: 1.1
Name: beegarden
Version: 2.2.9
Summary: The package allows you to create Beegarden game for programmers.
Home-page: https://github.com/suguby/beegarden
Author: Shandrinov Vadim
Author-email: suguby@gmail.com
License: BSD License
Platform: UNKNOWN
Classifier: Development Status :: 4 - Beta
Classifier: License :: OSI Approved :: BSD License
Classifier: Programming Language :: Python
Classifier: Programming Language :: Python :: 2.7
